maputil/__init__.py
maputil/map2.py
bfg_maputil-0.5.3.dist-info/METADATA
bfg_maputil-0.5.3.dist-info/WHEEL
bfg_maputil-0.5.3.dist-info/RECORD
