Metadata-Version: 2.4
Name: bfg-maputil
Version: 0.5.3
Summary: Threaded map for lists, pandas Series/DataFrames with index and progress
Author-email: leizha <8961794+leizha@users.noreply.github.com>
Requires-Python: >=3.10
Requires-Dist: pandas
Requires-Dist: tqdm
Provides-Extra: test
Requires-Dist: pytest; extra == 'test'
